[
  {
    "id": "product-1",
    "name": "Apple Macbook Air 13",
    "Type":"Notebook",
    "ram": "8GB",
    "core": "I5",
    "screen_size": "13 inch",
    "price_USD": 850,
    "stock": 6, 
    "picture": "https://www.notebookcheck.org/uploads/tx_nbc2/design_unibody2_20101020_02.png"
  },
  {
    "id": "product-2",
    "name": "Dell Inspiron 15",
    "Type":"Notebook",
    "ram": "8GB",
    "core": "I5",
    "screen_size": "15.6 inch",
    "price_USD": 650,
    "stock": 3,
    "picture": "https://www.todonotebook.com.ar/wp-content/uploads/2019/07/5593-i7.jpg"
  },
  {
    "id": "product-3",
    "name": "Hp 15",
    "Type":"Notebook",
    "ram": "8GB",
    "core": "I5",
    "screen_size": "15.6 inch",
    "price_USD": 780,
    "stock": 3,
    "picture": "https://ssl-product-images.www8-hp.com/digmedialib/prodimg/lowres/c06439201.png"
  },
  {
    "id": "product-4",
    "name": "Lenovo Ideapad Flex 5",
    "Type":"Notebook",
    "ram": "8GB",
    "core": "I3",
    "screen_size": "14 inch",
    "price_USD": 500,
    "stock": 4,
    "picture": "https://www.lenovo.com/medias/lenovo-laptop-ideapad-flex-5-13-subseries-hero.png?context=bWFzdGVyfHJvb3R8NTI4NjR8aW1hZ2UvcG5nfGhlYS9oZWMvMTA4MzA0MTg2NzM2OTQucG5nfGI1YTViYmVhZTRhNDdjNjcyOGM2MjBhM2E5ZGY0OGY4YTE1MjRlM2U4ZjFkNmFiM2M2NWIwMDEzYzRkMDg5N2M"
  },
  {
    "id": "product-5",
    "name": "Acer R53550h Nitro 5 ",
    "Type":"Notebook",
    "ram": "8GB",
    "core": "Ryzen 5",
    "screen_size": "15 inch",
    "price_USD": 850,
    "stock": 5,
    "picture": "https://i.blogs.es/ffc00c/acer-nitro-5-1-1/450_1000.jpg"
  },

  {
    "id": "product-6",
    "name": "HDD Western Digital WD Elements",
    "Type":"HDD",
    "ram": "1TB",
    "price_USD": 30,
    "stock": 12,
    "picture":"https://www.mgtecnologia.com.ar/images/DISCO-DURO-EXTERNO-1TB-WD-ELEMENTS-USB-3.01599006340757.jpg"
  },
  {
    "id": "product-7",
    "name": "HDD Sandick Extreme Portable",
    "Type":"HDD",
    "ram": "2TB",
    "price_USD": 45,
    "stock": 6,
    "picture":"https://media.ldlc.com/r1600/ld/products/00/05/54/76/LD0005547621_2.jpg"

  },
  {
    "id": "product-8",
    "name": "HDD Seagate Expansion",
    "Type":"HDD",
    "ram": "5TB",
    "price_USD": 60,
    "stock": 9,
    "picture":"https://www.fullh4rd.com.ar/img/productos/Pics_Prod/hd-usb-5tb-seagate-expansion-stea5000402-0.jpg"

  },
  {
    "id": "product-9",
    "name": "HDD Canvio Basic ",
    "Type":"HDD",
    "ram": "2TB",
    "price_USD": 20,
    "stock": 2,
    "picture":"http://www.infor-alhambra.com/1471-home_default/disco-duro-externo-2tb-maxtor.jpg"
  }
]
